{
	"credit": "Made with Blockbench",
	"texture_size": [32, 32],
	"textures": {
		"0": "cozy:block/pizza/cooked_pizza_dough_base",
		"particle": "cozy:block/pizza/cooked_pizza_dough_base"
	},
	"elements": [
		{
			"from": [8, 0, 1],
			"to": [15, 1, 8],
			"faces": {
				"north": {"uv": [7, 0, 10.5, 0.5], "texture": "#0"},
				"east": {"uv": [7, 0, 10.5, 0.5], "texture": "#0"},
				"south": {"uv": [10.5, 2, 12.25, 2.25], "texture": "#0"},
				"west": {"uv": [7, 0, 10.5, 0.5], "texture": "#0"},
				"up": {"uv": [3.5, 7, 0, 3.5], "texture": "#0"},
				"down": {"uv": [3.5, 10.45, 0, 13.95], "texture": "#0"}
			}
		},
		{
			"from": [1, 0, 8],
			"to": [15, 1, 15],
			"faces": {
				"north": {"uv": [7, 0, 14, 0.5], "texture": "#0"},
				"east": {"uv": [10.5, 0, 14, 0.5], "texture": "#0"},
				"south": {"uv": [7, 0, 14, 0.5], "texture": "#0"},
				"west": {"uv": [10.5, 0, 14, 0.5], "texture": "#0"},
				"up": {"uv": [0, 3.5, 7, 0], "texture": "#0"},
				"down": {"uv": [7, 7, 0, 10.5], "texture": "#0"}
			}
		}
	]
}